cornershot/__init__.py
cornershot/__main__.py
cornershot/cornershot.py
cornershot/shots/__init__.py
cornershot/shots/even.py
cornershot/shots/even6.py
cornershot/shots/rprn.py
cornershot/shots/rrp.py
cornershot-0.3.0.dist-info/LICENSE.txt
cornershot-0.3.0.dist-info/METADATA
cornershot-0.3.0.dist-info/WHEEL
cornershot-0.3.0.dist-info/top_level.txt
cornershot-0.3.0.dist-info/RECORD
